_lsap/_lsap_module.cpp
_lsap/rectangular_lsap.cpp
_lsap/rectangular_lsap.h
minilsap/__init__.py
minilsap/_lsap.pyd
minilsap/_version.py
minilsap/solver.py
minilsap-1.0.1.dist-info/licenses/LICENSE
minilsap-1.0.1.dist-info/METADATA
minilsap-1.0.1.dist-info/WHEEL
minilsap-1.0.1.dist-info/top_level.txt
minilsap-1.0.1.dist-info/RECORD
