Metadata-Version: 2.4
Name: minilsap
Version: 1.0.1
Summary: Python module to solve the linear sum assignment problem (LSAP) efficiently
Maintainer-email: Tamas Nepusz <tamas@collmot.com>
License-Expression: BSD-3-Clause
Project-URL: homepage, https://github.com/ntamas/lsap
Keywords: lsap,munkres,kuhn-munkres,linear sum assignment problem
Classifier: Development Status :: 5 - Production/Stable
Classifier: Programming Language :: Python :: 3
Classifier: Programming Language :: Python :: 3.10
Classifier: Programming Language :: Python :: 3.11
Classifier: Programming Language :: Python :: 3.12
Classifier: Programming Language :: Python :: 3.13
Classifier: Programming Language :: Python :: 3.14
Requires-Python: >=3.10
License-File: LICENSE
Requires-Dist: numpy>=1.21.0
Dynamic: license-file
